{
    "Current Match": 665,
    "Matches": [
        {
            "Match Number": 0,
            "Damage done": 0.0
        },
        {
            "Match Number": 1,
            "Damage done": 44.0
        },
        {
            "Match Number": 2,
            "Damage done": 44.0
        },
        {
            "Match Number": 3,
            "Damage done": 77.0
        },
        {
            "Match Number": 4,
            "Damage done": 80.0
        },
        {
            "Match Number": 5,
            "Damage done": 85.0
        },
        {
            "Match Number": 6,
            "Damage done": 95.0
        },
        {
            "Match Number": 7,
            "Damage done": 89.0
        },
        {
            "Match Number": 8,
            "Damage done": 84.0
        },
        {
            "Match Number": 9,
            "Damage done": 81.0
        },
        {
            "Match Number": 10,
            "Damage done": 19.0
        },
        {
            "Match Number": 11,
            "Damage done": 147.0
        },
        {
            "Match Number": 12,
            "Damage done": 68.0
        },
        {
            "Match Number": 13,
            "Damage done": 24.0
        },
        {
            "Match Number": 14,
            "Damage done": 32.0
        },
        {
            "Match Number": 15,
            "Damage done": 120.0
        },
        {
            "Match Number": 16,
            "Damage done": 32.0
        },
        {
            "Match Number": 17,
            "Damage done": 16.0
        },
        {
            "Match Number": 18,
            "Damage done": 88.0
        },
        {
            "Match Number": 19,
            "Damage done": 83.0
        },
        {
            "Match Number": 20,
            "Damage done": 17.0
        },
        {
            "Match Number": 21,
            "Damage done": 82.0
        },
        {
            "Match Number": 22,
            "Damage done": 13.0
        },
        {
            "Match Number": 23,
            "Damage done": 33.0
        },
        {
            "Match Number": 24,
            "Damage done": 65.0
        },
        {
            "Match Number": 25,
            "Damage done": 37.0
        },
        {
            "Match Number": 26,
            "Damage done": 4.0
        },
        {
            "Match Number": 27,
            "Damage done": 0.0
        },
        {
            "Match Number": 28,
            "Damage done": 34.0
        },
        {
            "Match Number": 29,
            "Damage done": 21.0
        },
        {
            "Match Number": 30,
            "Damage done": 60.0
        },
        {
            "Match Number": 31,
            "Damage done": 44.0
        },
        {
            "Match Number": 32,
            "Damage done": 15.0
        },
        {
            "Match Number": 33,
            "Damage done": 101.0
        },
        {
            "Match Number": 34,
            "Damage done": 73.0
        },
        {
            "Match Number": 35,
            "Damage done": 11.0
        },
        {
            "Match Number": 36,
            "Damage done": 112.0
        },
        {
            "Match Number": 37,
            "Damage done": 96.0
        },
        {
            "Match Number": 38,
            "Damage done": 31.0
        },
        {
            "Match Number": 39,
            "Damage done": 36.0
        },
        {
            "Match Number": 40,
            "Damage done": 71.0
        },
        {
            "Match Number": 41,
            "Damage done": 103.0
        },
        {
            "Match Number": 42,
            "Damage done": 8.0
        },
        {
            "Match Number": 43,
            "Damage done": 26.0
        },
        {
            "Match Number": 44,
            "Damage done": 83.0
        },
        {
            "Match Number": 45,
            "Damage done": 55.0
        },
        {
            "Match Number": 46,
            "Damage done": 64.0
        },
        {
            "Match Number": 47,
            "Damage done": 67.0
        },
        {
            "Match Number": 48,
            "Damage done": 44.0
        },
        {
            "Match Number": 49,
            "Damage done": 36.0
        },
        {
            "Match Number": 50,
            "Damage done": 78.0
        },
        {
            "Match Number": 51,
            "Damage done": 101.0
        },
        {
            "Match Number": 52,
            "Damage done": 18.0
        },
        {
            "Match Number": 53,
            "Damage done": 36.0
        },
        {
            "Match Number": 54,
            "Damage done": 36.0
        },
        {
            "Match Number": 55,
            "Damage done": 98.0
        },
        {
            "Match Number": 56,
            "Damage done": 41.0
        },
        {
            "Match Number": 57,
            "Damage done": 59.0
        },
        {
            "Match Number": 58,
            "Damage done": 84.0
        },
        {
            "Match Number": 59,
            "Damage done": 8.0
        },
        {
            "Match Number": 60,
            "Damage done": 16.0
        },
        {
            "Match Number": 61,
            "Damage done": 0.0
        },
        {
            "Match Number": 62,
            "Damage done": 0.0
        },
        {
            "Match Number": 63,
            "Damage done": 13.0
        },
        {
            "Match Number": 64,
            "Damage done": 65.0
        },
        {
            "Match Number": 65,
            "Damage done": 106.0
        },
        {
            "Match Number": 66,
            "Damage done": 57.0
        },
        {
            "Match Number": 67,
            "Damage done": 61.0
        },
        {
            "Match Number": 68,
            "Damage done": 68.0
        },
        {
            "Match Number": 69,
            "Damage done": 0.0
        },
        {
            "Match Number": 70,
            "Damage done": 72.0
        },
        {
            "Match Number": 71,
            "Damage done": 6.0
        },
        {
            "Match Number": 72,
            "Damage done": 48.0
        },
        {
            "Match Number": 73,
            "Damage done": 201.0
        },
        {
            "Match Number": 74,
            "Damage done": 42.0
        },
        {
            "Match Number": 75,
            "Damage done": 24.0
        },
        {
            "Match Number": 76,
            "Damage done": 26.0
        },
        {
            "Match Number": 77,
            "Damage done": 85.0
        },
        {
            "Match Number": 78,
            "Damage done": 4.0
        },
        {
            "Match Number": 79,
            "Damage done": 82.0
        },
        {
            "Match Number": 80,
            "Damage done": 65.0
        },
        {
            "Match Number": 81,
            "Damage done": 48.0
        },
        {
            "Match Number": 82,
            "Damage done": 73.0
        },
        {
            "Match Number": 83,
            "Damage done": 11.0
        },
        {
            "Match Number": 84,
            "Damage done": 211.0
        },
        {
            "Match Number": 85,
            "Damage done": 89.0
        },
        {
            "Match Number": 86,
            "Damage done": 126.0
        },
        {
            "Match Number": 87,
            "Damage done": 112.0
        },
        {
            "Match Number": 88,
            "Damage done": 11.0
        },
        {
            "Match Number": 89,
            "Damage done": 37.0
        },
        {
            "Match Number": 90,
            "Damage done": 36.0
        },
        {
            "Match Number": 91,
            "Damage done": 28.0
        },
        {
            "Match Number": 92,
            "Damage done": 0.0
        },
        {
            "Match Number": 93,
            "Damage done": 6.0
        },
        {
            "Match Number": 94,
            "Damage done": 94.0
        },
        {
            "Match Number": 95,
            "Damage done": 0.0
        },
        {
            "Match Number": 96,
            "Damage done": 32.0
        },
        {
            "Match Number": 97,
            "Damage done": 43.0
        },
        {
            "Match Number": 98,
            "Damage done": 51.0
        },
        {
            "Match Number": 99,
            "Damage done": 22.0
        },
        {
            "Match Number": 100,
            "Damage done": 0.0
        },
        {
            "Match Number": 101,
            "Damage done": 27.0
        },
        {
            "Match Number": 102,
            "Damage done": 118.0
        },
        {
            "Match Number": 103,
            "Damage done": 0.0
        },
        {
            "Match Number": 104,
            "Damage done": 19.0
        },
        {
            "Match Number": 105,
            "Damage done": 48.0
        },
        {
            "Match Number": 106,
            "Damage done": 25.0
        },
        {
            "Match Number": 107,
            "Damage done": 73.0
        },
        {
            "Match Number": 108,
            "Damage done": 45.0
        },
        {
            "Match Number": 109,
            "Damage done": 27.0
        },
        {
            "Match Number": 110,
            "Damage done": 47.0
        },
        {
            "Match Number": 111,
            "Damage done": 119.0
        },
        {
            "Match Number": 112,
            "Damage done": 34.0
        },
        {
            "Match Number": 113,
            "Damage done": 114.0
        },
        {
            "Match Number": 114,
            "Damage done": 112.0
        },
        {
            "Match Number": 115,
            "Damage done": 115.0
        },
        {
            "Match Number": 116,
            "Damage done": 12.0
        },
        {
            "Match Number": 117,
            "Damage done": 57.0
        },
        {
            "Match Number": 118,
            "Damage done": 48.0
        },
        {
            "Match Number": 119,
            "Damage done": 23.0
        },
        {
            "Match Number": 120,
            "Damage done": 135.0
        },
        {
            "Match Number": 121,
            "Damage done": 48.0
        },
        {
            "Match Number": 122,
            "Damage done": 39.0
        },
        {
            "Match Number": 123,
            "Damage done": 56.0
        },
        {
            "Match Number": 124,
            "Damage done": 71.0
        },
        {
            "Match Number": 125,
            "Damage done": 81.0
        },
        {
            "Match Number": 126,
            "Damage done": 80.0
        },
        {
            "Match Number": 127,
            "Damage done": 54.0
        },
        {
            "Match Number": 128,
            "Damage done": 61.0
        },
        {
            "Match Number": 129,
            "Damage done": 30.0
        },
        {
            "Match Number": 130,
            "Damage done": 39.0
        },
        {
            "Match Number": 131,
            "Damage done": 27.0
        },
        {
            "Match Number": 132,
            "Damage done": 70.0
        },
        {
            "Match Number": 133,
            "Damage done": 84.0
        },
        {
            "Match Number": 134,
            "Damage done": 19.0
        },
        {
            "Match Number": 135,
            "Damage done": 43.0
        },
        {
            "Match Number": 136,
            "Damage done": 19.0
        },
        {
            "Match Number": 137,
            "Damage done": 42.0
        },
        {
            "Match Number": 138,
            "Damage done": 33.0
        },
        {
            "Match Number": 139,
            "Damage done": 43.0
        },
        {
            "Match Number": 140,
            "Damage done": 190.0
        },
        {
            "Match Number": 141,
            "Damage done": 61.0
        },
        {
            "Match Number": 142,
            "Damage done": 5.0
        },
        {
            "Match Number": 143,
            "Damage done": 47.0
        },
        {
            "Match Number": 144,
            "Damage done": 0.0
        },
        {
            "Match Number": 145,
            "Damage done": 94.0
        },
        {
            "Match Number": 146,
            "Damage done": 48.0
        },
        {
            "Match Number": 147,
            "Damage done": 15.0
        },
        {
            "Match Number": 148,
            "Damage done": 23.0
        },
        {
            "Match Number": 149,
            "Damage done": 6.0
        },
        {
            "Match Number": 150,
            "Damage done": 143.0
        },
        {
            "Match Number": 151,
            "Damage done": 50.0
        },
        {
            "Match Number": 152,
            "Damage done": 36.0
        },
        {
            "Match Number": 153,
            "Damage done": 114.0
        },
        {
            "Match Number": 154,
            "Damage done": 46.0
        },
        {
            "Match Number": 155,
            "Damage done": 44.0
        },
        {
            "Match Number": 156,
            "Damage done": 30.0
        },
        {
            "Match Number": 157,
            "Damage done": 123.0
        },
        {
            "Match Number": 158,
            "Damage done": 103.0
        },
        {
            "Match Number": 159,
            "Damage done": 49.0
        },
        {
            "Match Number": 160,
            "Damage done": 65.0
        },
        {
            "Match Number": 161,
            "Damage done": 8.0
        },
        {
            "Match Number": 162,
            "Damage done": 109.0
        },
        {
            "Match Number": 163,
            "Damage done": 40.0
        },
        {
            "Match Number": 164,
            "Damage done": 56.0
        },
        {
            "Match Number": 165,
            "Damage done": 116.0
        },
        {
            "Match Number": 166,
            "Damage done": 0.0
        },
        {
            "Match Number": 167,
            "Damage done": 56.0
        },
        {
            "Match Number": 168,
            "Damage done": 47.0
        },
        {
            "Match Number": 169,
            "Damage done": 76.0
        },
        {
            "Match Number": 170,
            "Damage done": 22.0
        },
        {
            "Match Number": 171,
            "Damage done": 124.0
        },
        {
            "Match Number": 172,
            "Damage done": 111.0
        },
        {
            "Match Number": 173,
            "Damage done": 171.0
        },
        {
            "Match Number": 174,
            "Damage done": 42.0
        },
        {
            "Match Number": 175,
            "Damage done": 77.0
        },
        {
            "Match Number": 176,
            "Damage done": 37.0
        },
        {
            "Match Number": 177,
            "Damage done": 0.0
        },
        {
            "Match Number": 178,
            "Damage done": 42.0
        },
        {
            "Match Number": 179,
            "Damage done": 27.0
        },
        {
            "Match Number": 180,
            "Damage done": 74.0
        },
        {
            "Match Number": 181,
            "Damage done": 97.0
        },
        {
            "Match Number": 182,
            "Damage done": 106.0
        },
        {
            "Match Number": 183,
            "Damage done": 62.0
        },
        {
            "Match Number": 184,
            "Damage done": 55.0
        },
        {
            "Match Number": 185,
            "Damage done": 91.0
        },
        {
            "Match Number": 186,
            "Damage done": 71.0
        },
        {
            "Match Number": 187,
            "Damage done": 88.0
        },
        {
            "Match Number": 188,
            "Damage done": 175.0
        },
        {
            "Match Number": 189,
            "Damage done": 75.0
        },
        {
            "Match Number": 190,
            "Damage done": 45.0
        },
        {
            "Match Number": 191,
            "Damage done": 47.0
        },
        {
            "Match Number": 192,
            "Damage done": 62.0
        },
        {
            "Match Number": 193,
            "Damage done": 156.0
        },
        {
            "Match Number": 194,
            "Damage done": 83.0
        },
        {
            "Match Number": 195,
            "Damage done": 178.0
        },
        {
            "Match Number": 196,
            "Damage done": 84.0
        },
        {
            "Match Number": 197,
            "Damage done": 133.0
        },
        {
            "Match Number": 198,
            "Damage done": 68.0
        },
        {
            "Match Number": 199,
            "Damage done": 15.0
        },
        {
            "Match Number": 200,
            "Damage done": 61.0
        },
        {
            "Match Number": 201,
            "Damage done": 11.0
        },
        {
            "Match Number": 202,
            "Damage done": 67.0
        },
        {
            "Match Number": 203,
            "Damage done": 64.0
        },
        {
            "Match Number": 204,
            "Damage done": 97.0
        },
        {
            "Match Number": 205,
            "Damage done": 29.0
        },
        {
            "Match Number": 206,
            "Damage done": 142.0
        },
        {
            "Match Number": 207,
            "Damage done": 121.0
        },
        {
            "Match Number": 208,
            "Damage done": 146.0
        },
        {
            "Match Number": 209,
            "Damage done": 66.0
        },
        {
            "Match Number": 210,
            "Damage done": 108.0
        },
        {
            "Match Number": 211,
            "Damage done": 61.0
        },
        {
            "Match Number": 212,
            "Damage done": 96.0
        },
        {
            "Match Number": 213,
            "Damage done": 123.0
        },
        {
            "Match Number": 214,
            "Damage done": 66.0
        },
        {
            "Match Number": 215,
            "Damage done": 51.0
        },
        {
            "Match Number": 216,
            "Damage done": 83.0
        },
        {
            "Match Number": 217,
            "Damage done": 36.0
        },
        {
            "Match Number": 218,
            "Damage done": 98.0
        },
        {
            "Match Number": 219,
            "Damage done": 108.0
        },
        {
            "Match Number": 220,
            "Damage done": 100.0
        },
        {
            "Match Number": 221,
            "Damage done": 22.0
        },
        {
            "Match Number": 222,
            "Damage done": 105.0
        },
        {
            "Match Number": 223,
            "Damage done": 68.0
        },
        {
            "Match Number": 224,
            "Damage done": 127.0
        },
        {
            "Match Number": 225,
            "Damage done": 95.0
        },
        {
            "Match Number": 226,
            "Damage done": 89.0
        },
        {
            "Match Number": 227,
            "Damage done": 21.0
        },
        {
            "Match Number": 228,
            "Damage done": 100.0
        },
        {
            "Match Number": 229,
            "Damage done": 75.0
        },
        {
            "Match Number": 230,
            "Damage done": 35.0
        },
        {
            "Match Number": 231,
            "Damage done": 58.0
        },
        {
            "Match Number": 232,
            "Damage done": 110.0
        },
        {
            "Match Number": 233,
            "Damage done": 84.0
        },
        {
            "Match Number": 234,
            "Damage done": 41.0
        },
        {
            "Match Number": 235,
            "Damage done": 10.0
        },
        {
            "Match Number": 236,
            "Damage done": 96.0
        },
        {
            "Match Number": 237,
            "Damage done": 47.0
        },
        {
            "Match Number": 238,
            "Damage done": 69.0
        },
        {
            "Match Number": 239,
            "Damage done": 83.0
        },
        {
            "Match Number": 240,
            "Damage done": 21.0
        },
        {
            "Match Number": 241,
            "Damage done": 71.0
        },
        {
            "Match Number": 242,
            "Damage done": 95.0
        },
        {
            "Match Number": 243,
            "Damage done": 31.0
        },
        {
            "Match Number": 244,
            "Damage done": 66.0
        },
        {
            "Match Number": 245,
            "Damage done": 132.0
        },
        {
            "Match Number": 246,
            "Damage done": 66.0
        },
        {
            "Match Number": 247,
            "Damage done": 130.0
        },
        {
            "Match Number": 248,
            "Damage done": 8.0
        },
        {
            "Match Number": 249,
            "Damage done": 43.0
        },
        {
            "Match Number": 250,
            "Damage done": 31.0
        },
        {
            "Match Number": 251,
            "Damage done": 58.0
        },
        {
            "Match Number": 252,
            "Damage done": 74.0
        },
        {
            "Match Number": 253,
            "Damage done": 50.0
        },
        {
            "Match Number": 254,
            "Damage done": 72.0
        },
        {
            "Match Number": 255,
            "Damage done": 10.0
        },
        {
            "Match Number": 256,
            "Damage done": 38.0
        },
        {
            "Match Number": 257,
            "Damage done": 95.0
        },
        {
            "Match Number": 258,
            "Damage done": 71.0
        },
        {
            "Match Number": 259,
            "Damage done": 168.0
        },
        {
            "Match Number": 260,
            "Damage done": 29.0
        },
        {
            "Match Number": 261,
            "Damage done": 68.0
        },
        {
            "Match Number": 262,
            "Damage done": 10.0
        },
        {
            "Match Number": 263,
            "Damage done": 88.0
        },
        {
            "Match Number": 264,
            "Damage done": 93.0
        },
        {
            "Match Number": 265,
            "Damage done": 99.0
        },
        {
            "Match Number": 266,
            "Damage done": 60.0
        },
        {
            "Match Number": 267,
            "Damage done": 96.0
        },
        {
            "Match Number": 268,
            "Damage done": 49.0
        },
        {
            "Match Number": 269,
            "Damage done": 109.0
        },
        {
            "Match Number": 270,
            "Damage done": 70.0
        },
        {
            "Match Number": 271,
            "Damage done": 83.0
        },
        {
            "Match Number": 272,
            "Damage done": 126.0
        },
        {
            "Match Number": 273,
            "Damage done": 34.0
        },
        {
            "Match Number": 274,
            "Damage done": 103.0
        },
        {
            "Match Number": 275,
            "Damage done": 71.0
        },
        {
            "Match Number": 276,
            "Damage done": 29.0
        },
        {
            "Match Number": 277,
            "Damage done": 98.0
        },
        {
            "Match Number": 278,
            "Damage done": 60.0
        },
        {
            "Match Number": 279,
            "Damage done": 77.0
        },
        {
            "Match Number": 280,
            "Damage done": 50.0
        },
        {
            "Match Number": 281,
            "Damage done": 47.0
        },
        {
            "Match Number": 282,
            "Damage done": 91.0
        },
        {
            "Match Number": 283,
            "Damage done": 98.0
        },
        {
            "Match Number": 284,
            "Damage done": 50.0
        },
        {
            "Match Number": 285,
            "Damage done": 79.0
        },
        {
            "Match Number": 286,
            "Damage done": 38.0
        },
        {
            "Match Number": 287,
            "Damage done": 64.0
        },
        {
            "Match Number": 288,
            "Damage done": 74.0
        },
        {
            "Match Number": 289,
            "Damage done": 66.0
        },
        {
            "Match Number": 290,
            "Damage done": 123.0
        },
        {
            "Match Number": 291,
            "Damage done": 109.0
        },
        {
            "Match Number": 292,
            "Damage done": 167.0
        },
        {
            "Match Number": 293,
            "Damage done": 107.0
        },
        {
            "Match Number": 294,
            "Damage done": 125.0
        },
        {
            "Match Number": 295,
            "Damage done": 74.0
        },
        {
            "Match Number": 296,
            "Damage done": 39.0
        },
        {
            "Match Number": 297,
            "Damage done": 172.0
        },
        {
            "Match Number": 298,
            "Damage done": 31.0
        },
        {
            "Match Number": 299,
            "Damage done": 25.0
        },
        {
            "Match Number": 300,
            "Damage done": 94.0
        },
        {
            "Match Number": 301,
            "Damage done": 14.0
        },
        {
            "Match Number": 302,
            "Damage done": 52.0
        },
        {
            "Match Number": 303,
            "Damage done": 18.0
        },
        {
            "Match Number": 304,
            "Damage done": 70.0
        },
        {
            "Match Number": 305,
            "Damage done": 113.0
        },
        {
            "Match Number": 306,
            "Damage done": 72.0
        },
        {
            "Match Number": 307,
            "Damage done": 54.0
        },
        {
            "Match Number": 308,
            "Damage done": 176.0
        },
        {
            "Match Number": 309,
            "Damage done": 30.0
        },
        {
            "Match Number": 310,
            "Damage done": 22.0
        },
        {
            "Match Number": 311,
            "Damage done": 41.0
        },
        {
            "Match Number": 312,
            "Damage done": 59.0
        },
        {
            "Match Number": 313,
            "Damage done": 37.0
        },
        {
            "Match Number": 314,
            "Damage done": 169.0
        },
        {
            "Match Number": 315,
            "Damage done": 78.0
        },
        {
            "Match Number": 316,
            "Damage done": 6.0
        },
        {
            "Match Number": 317,
            "Damage done": 204.0
        },
        {
            "Match Number": 318,
            "Damage done": 23.0
        },
        {
            "Match Number": 319,
            "Damage done": 50.0
        },
        {
            "Match Number": 320,
            "Damage done": 115.0
        },
        {
            "Match Number": 321,
            "Damage done": 143.0
        },
        {
            "Match Number": 322,
            "Damage done": 70.0
        },
        {
            "Match Number": 323,
            "Damage done": 52.0
        },
        {
            "Match Number": 324,
            "Damage done": 60.0
        },
        {
            "Match Number": 325,
            "Damage done": 82.0
        },
        {
            "Match Number": 326,
            "Damage done": 31.0
        },
        {
            "Match Number": 327,
            "Damage done": 163.0
        },
        {
            "Match Number": 328,
            "Damage done": 52.0
        },
        {
            "Match Number": 329,
            "Damage done": 129.0
        },
        {
            "Match Number": 330,
            "Damage done": 111.0
        },
        {
            "Match Number": 331,
            "Damage done": 42.0
        },
        {
            "Match Number": 332,
            "Damage done": 48.0
        },
        {
            "Match Number": 333,
            "Damage done": 72.0
        },
        {
            "Match Number": 334,
            "Damage done": 47.0
        },
        {
            "Match Number": 335,
            "Damage done": 75.0
        },
        {
            "Match Number": 336,
            "Damage done": 166.0
        },
        {
            "Match Number": 337,
            "Damage done": 49.0
        },
        {
            "Match Number": 338,
            "Damage done": 20.0
        },
        {
            "Match Number": 339,
            "Damage done": 131.0
        },
        {
            "Match Number": 340,
            "Damage done": 82.0
        },
        {
            "Match Number": 341,
            "Damage done": 139.0
        },
        {
            "Match Number": 342,
            "Damage done": 63.0
        },
        {
            "Match Number": 343,
            "Damage done": 9.0
        },
        {
            "Match Number": 344,
            "Damage done": 56.0
        },
        {
            "Match Number": 345,
            "Damage done": 221.0
        },
        {
            "Match Number": 346,
            "Damage done": 94.0
        },
        {
            "Match Number": 347,
            "Damage done": 23.0
        },
        {
            "Match Number": 348,
            "Damage done": 77.0
        },
        {
            "Match Number": 349,
            "Damage done": 41.0
        },
        {
            "Match Number": 350,
            "Damage done": 94.0
        },
        {
            "Match Number": 351,
            "Damage done": 92.0
        },
        {
            "Match Number": 352,
            "Damage done": 23.0
        },
        {
            "Match Number": 353,
            "Damage done": 21.0
        },
        {
            "Match Number": 354,
            "Damage done": 158.0
        },
        {
            "Match Number": 355,
            "Damage done": 89.0
        },
        {
            "Match Number": 356,
            "Damage done": 134.0
        },
        {
            "Match Number": 357,
            "Damage done": 61.0
        },
        {
            "Match Number": 358,
            "Damage done": 36.0
        },
        {
            "Match Number": 359,
            "Damage done": 66.0
        },
        {
            "Match Number": 360,
            "Damage done": 33.0
        },
        {
            "Match Number": 361,
            "Damage done": 33.0
        },
        {
            "Match Number": 362,
            "Damage done": 66.0
        },
        {
            "Match Number": 363,
            "Damage done": 36.0
        },
        {
            "Match Number": 364,
            "Damage done": 92.0
        },
        {
            "Match Number": 365,
            "Damage done": 128.0
        },
        {
            "Match Number": 366,
            "Damage done": 32.0
        },
        {
            "Match Number": 367,
            "Damage done": 79.0
        },
        {
            "Match Number": 368,
            "Damage done": 86.0
        },
        {
            "Match Number": 369,
            "Damage done": 112.0
        },
        {
            "Match Number": 370,
            "Damage done": 170.0
        },
        {
            "Match Number": 371,
            "Damage done": 16.0
        },
        {
            "Match Number": 372,
            "Damage done": 56.0
        },
        {
            "Match Number": 373,
            "Damage done": 66.0
        },
        {
            "Match Number": 374,
            "Damage done": 87.0
        },
        {
            "Match Number": 375,
            "Damage done": 186.0
        },
        {
            "Match Number": 376,
            "Damage done": 109.0
        },
        {
            "Match Number": 377,
            "Damage done": 10.0
        },
        {
            "Match Number": 378,
            "Damage done": 43.0
        },
        {
            "Match Number": 379,
            "Damage done": 57.0
        },
        {
            "Match Number": 380,
            "Damage done": 34.0
        },
        {
            "Match Number": 381,
            "Damage done": 99.0
        },
        {
            "Match Number": 382,
            "Damage done": 15.0
        },
        {
            "Match Number": 383,
            "Damage done": 52.0
        },
        {
            "Match Number": 384,
            "Damage done": 54.0
        },
        {
            "Match Number": 385,
            "Damage done": 21.0
        },
        {
            "Match Number": 386,
            "Damage done": 91.0
        },
        {
            "Match Number": 387,
            "Damage done": 88.0
        },
        {
            "Match Number": 388,
            "Damage done": 117.0
        },
        {
            "Match Number": 389,
            "Damage done": 44.0
        },
        {
            "Match Number": 390,
            "Damage done": 86.0
        },
        {
            "Match Number": 391,
            "Damage done": 46.0
        },
        {
            "Match Number": 392,
            "Damage done": 133.0
        },
        {
            "Match Number": 393,
            "Damage done": 27.0
        },
        {
            "Match Number": 394,
            "Damage done": 137.0
        },
        {
            "Match Number": 395,
            "Damage done": 52.0
        },
        {
            "Match Number": 396,
            "Damage done": 46.0
        },
        {
            "Match Number": 397,
            "Damage done": 22.0
        },
        {
            "Match Number": 398,
            "Damage done": 15.0
        },
        {
            "Match Number": 399,
            "Damage done": 116.0
        },
        {
            "Match Number": 400,
            "Damage done": 66.0
        },
        {
            "Match Number": 401,
            "Damage done": 117.0
        },
        {
            "Match Number": 402,
            "Damage done": 96.0
        },
        {
            "Match Number": 403,
            "Damage done": 31.0
        },
        {
            "Match Number": 404,
            "Damage done": 0.0
        },
        {
            "Match Number": 405,
            "Damage done": 58.0
        },
        {
            "Match Number": 406,
            "Damage done": 102.0
        },
        {
            "Match Number": 407,
            "Damage done": 53.0
        },
        {
            "Match Number": 408,
            "Damage done": 157.0
        },
        {
            "Match Number": 409,
            "Damage done": 38.0
        },
        {
            "Match Number": 410,
            "Damage done": 183.0
        },
        {
            "Match Number": 411,
            "Damage done": 116.0
        },
        {
            "Match Number": 412,
            "Damage done": 153.0
        },
        {
            "Match Number": 413,
            "Damage done": 140.0
        },
        {
            "Match Number": 414,
            "Damage done": 12.0
        },
        {
            "Match Number": 415,
            "Damage done": 115.0
        },
        {
            "Match Number": 416,
            "Damage done": 4.0
        },
        {
            "Match Number": 417,
            "Damage done": 175.0
        },
        {
            "Match Number": 418,
            "Damage done": 124.0
        },
        {
            "Match Number": 419,
            "Damage done": 91.0
        },
        {
            "Match Number": 420,
            "Damage done": 153.0
        },
        {
            "Match Number": 421,
            "Damage done": 67.0
        },
        {
            "Match Number": 422,
            "Damage done": 67.0
        },
        {
            "Match Number": 423,
            "Damage done": 42.0
        },
        {
            "Match Number": 424,
            "Damage done": 46.0
        },
        {
            "Match Number": 425,
            "Damage done": 61.0
        },
        {
            "Match Number": 426,
            "Damage done": 97.0
        },
        {
            "Match Number": 427,
            "Damage done": 95.0
        },
        {
            "Match Number": 428,
            "Damage done": 44.0
        },
        {
            "Match Number": 429,
            "Damage done": 31.0
        },
        {
            "Match Number": 430,
            "Damage done": 41.0
        },
        {
            "Match Number": 431,
            "Damage done": 39.0
        },
        {
            "Match Number": 432,
            "Damage done": 138.0
        },
        {
            "Match Number": 433,
            "Damage done": 66.0
        },
        {
            "Match Number": 434,
            "Damage done": 159.0
        },
        {
            "Match Number": 435,
            "Damage done": 48.0
        },
        {
            "Match Number": 436,
            "Damage done": 115.0
        },
        {
            "Match Number": 437,
            "Damage done": 177.0
        },
        {
            "Match Number": 438,
            "Damage done": 61.0
        },
        {
            "Match Number": 439,
            "Damage done": 139.0
        },
        {
            "Match Number": 440,
            "Damage done": 141.0
        },
        {
            "Match Number": 441,
            "Damage done": 142.0
        },
        {
            "Match Number": 442,
            "Damage done": 27.0
        },
        {
            "Match Number": 443,
            "Damage done": 55.0
        },
        {
            "Match Number": 444,
            "Damage done": 134.0
        },
        {
            "Match Number": 445,
            "Damage done": 128.0
        },
        {
            "Match Number": 446,
            "Damage done": 72.0
        },
        {
            "Match Number": 447,
            "Damage done": 28.0
        },
        {
            "Match Number": 448,
            "Damage done": 98.0
        },
        {
            "Match Number": 449,
            "Damage done": 90.0
        },
        {
            "Match Number": 450,
            "Damage done": 78.0
        },
        {
            "Match Number": 451,
            "Damage done": 71.0
        },
        {
            "Match Number": 452,
            "Damage done": 50.0
        },
        {
            "Match Number": 453,
            "Damage done": 58.0
        },
        {
            "Match Number": 454,
            "Damage done": 41.0
        },
        {
            "Match Number": 455,
            "Damage done": 108.0
        },
        {
            "Match Number": 456,
            "Damage done": 74.0
        },
        {
            "Match Number": 457,
            "Damage done": 108.0
        },
        {
            "Match Number": 458,
            "Damage done": 48.0
        },
        {
            "Match Number": 459,
            "Damage done": 23.0
        },
        {
            "Match Number": 460,
            "Damage done": 110.0
        },
        {
            "Match Number": 461,
            "Damage done": 81.0
        },
        {
            "Match Number": 462,
            "Damage done": 170.0
        },
        {
            "Match Number": 463,
            "Damage done": 92.0
        },
        {
            "Match Number": 464,
            "Damage done": 135.0
        },
        {
            "Match Number": 465,
            "Damage done": 96.0
        },
        {
            "Match Number": 466,
            "Damage done": 161.0
        },
        {
            "Match Number": 467,
            "Damage done": 18.0
        },
        {
            "Match Number": 468,
            "Damage done": 61.0
        },
        {
            "Match Number": 469,
            "Damage done": 84.0
        },
        {
            "Match Number": 470,
            "Damage done": 55.0
        },
        {
            "Match Number": 471,
            "Damage done": 100.0
        },
        {
            "Match Number": 472,
            "Damage done": 13.0
        },
        {
            "Match Number": 473,
            "Damage done": 19.0
        },
        {
            "Match Number": 474,
            "Damage done": 99.0
        },
        {
            "Match Number": 475,
            "Damage done": 77.0
        },
        {
            "Match Number": 476,
            "Damage done": 63.0
        },
        {
            "Match Number": 477,
            "Damage done": 94.0
        },
        {
            "Match Number": 478,
            "Damage done": 27.0
        },
        {
            "Match Number": 479,
            "Damage done": 28.0
        },
        {
            "Match Number": 480,
            "Damage done": 68.0
        },
        {
            "Match Number": 481,
            "Damage done": 57.0
        },
        {
            "Match Number": 482,
            "Damage done": 81.0
        },
        {
            "Match Number": 483,
            "Damage done": 42.0
        },
        {
            "Match Number": 484,
            "Damage done": 0.0
        },
        {
            "Match Number": 485,
            "Damage done": 34.0
        },
        {
            "Match Number": 486,
            "Damage done": 43.0
        },
        {
            "Match Number": 487,
            "Damage done": 72.0
        },
        {
            "Match Number": 488,
            "Damage done": 65.0
        },
        {
            "Match Number": 489,
            "Damage done": 52.0
        },
        {
            "Match Number": 490,
            "Damage done": 71.0
        },
        {
            "Match Number": 491,
            "Damage done": 103.0
        },
        {
            "Match Number": 492,
            "Damage done": 160.0
        },
        {
            "Match Number": 493,
            "Damage done": 50.0
        },
        {
            "Match Number": 494,
            "Damage done": 118.0
        },
        {
            "Match Number": 495,
            "Damage done": 0.0
        },
        {
            "Match Number": 496,
            "Damage done": 164.0
        },
        {
            "Match Number": 497,
            "Damage done": 41.0
        },
        {
            "Match Number": 498,
            "Damage done": 168.0
        },
        {
            "Match Number": 499,
            "Damage done": 96.0
        },
        {
            "Match Number": 500,
            "Damage done": 136.0
        },
        {
            "Match Number": 501,
            "Damage done": 95.0
        },
        {
            "Match Number": 502,
            "Damage done": 70.0
        },
        {
            "Match Number": 503,
            "Damage done": 74.0
        },
        {
            "Match Number": 504,
            "Damage done": 20.0
        },
        {
            "Match Number": 505,
            "Damage done": 102.0
        },
        {
            "Match Number": 506,
            "Damage done": 184.0
        },
        {
            "Match Number": 507,
            "Damage done": 124.0
        },
        {
            "Match Number": 508,
            "Damage done": 11.0
        },
        {
            "Match Number": 509,
            "Damage done": 134.0
        },
        {
            "Match Number": 510,
            "Damage done": 83.0
        },
        {
            "Match Number": 511,
            "Damage done": 139.0
        },
        {
            "Match Number": 512,
            "Damage done": 40.0
        },
        {
            "Match Number": 513,
            "Damage done": 108.0
        },
        {
            "Match Number": 514,
            "Damage done": 105.0
        },
        {
            "Match Number": 515,
            "Damage done": 23.0
        },
        {
            "Match Number": 516,
            "Damage done": 69.0
        },
        {
            "Match Number": 517,
            "Damage done": 71.0
        },
        {
            "Match Number": 518,
            "Damage done": 72.0
        },
        {
            "Match Number": 519,
            "Damage done": 41.0
        },
        {
            "Match Number": 520,
            "Damage done": 74.0
        },
        {
            "Match Number": 521,
            "Damage done": 120.0
        },
        {
            "Match Number": 522,
            "Damage done": 21.0
        },
        {
            "Match Number": 523,
            "Damage done": 57.0
        },
        {
            "Match Number": 524,
            "Damage done": 52.0
        },
        {
            "Match Number": 525,
            "Damage done": 149.0
        },
        {
            "Match Number": 526,
            "Damage done": 120.0
        },
        {
            "Match Number": 527,
            "Damage done": 115.0
        },
        {
            "Match Number": 528,
            "Damage done": 74.0
        },
        {
            "Match Number": 529,
            "Damage done": 54.0
        },
        {
            "Match Number": 530,
            "Damage done": 174.0
        },
        {
            "Match Number": 531,
            "Damage done": 46.0
        },
        {
            "Match Number": 532,
            "Damage done": 95.0
        },
        {
            "Match Number": 533,
            "Damage done": 163.0
        },
        {
            "Match Number": 534,
            "Damage done": 111.0
        },
        {
            "Match Number": 535,
            "Damage done": 119.0
        },
        {
            "Match Number": 536,
            "Damage done": 54.0
        },
        {
            "Match Number": 537,
            "Damage done": 68.0
        },
        {
            "Match Number": 538,
            "Damage done": 71.0
        },
        {
            "Match Number": 539,
            "Damage done": 140.0
        },
        {
            "Match Number": 540,
            "Damage done": 46.0
        },
        {
            "Match Number": 541,
            "Damage done": 53.0
        },
        {
            "Match Number": 542,
            "Damage done": 69.0
        },
        {
            "Match Number": 543,
            "Damage done": 31.0
        },
        {
            "Match Number": 544,
            "Damage done": 51.0
        },
        {
            "Match Number": 545,
            "Damage done": 60.0
        },
        {
            "Match Number": 546,
            "Damage done": 131.0
        },
        {
            "Match Number": 547,
            "Damage done": 121.0
        },
        {
            "Match Number": 548,
            "Damage done": 120.0
        },
        {
            "Match Number": 549,
            "Damage done": 30.0
        },
        {
            "Match Number": 550,
            "Damage done": 202.0
        },
        {
            "Match Number": 551,
            "Damage done": 57.0
        },
        {
            "Match Number": 552,
            "Damage done": 53.0
        },
        {
            "Match Number": 553,
            "Damage done": 37.0
        },
        {
            "Match Number": 554,
            "Damage done": 163.0
        },
        {
            "Match Number": 555,
            "Damage done": 0.0
        },
        {
            "Match Number": 556,
            "Damage done": 35.0
        },
        {
            "Match Number": 557,
            "Damage done": 0.0
        },
        {
            "Match Number": 558,
            "Damage done": 8.0
        },
        {
            "Match Number": 559,
            "Damage done": 29.0
        },
        {
            "Match Number": 560,
            "Damage done": 49.0
        },
        {
            "Match Number": 561,
            "Damage done": 198.0
        },
        {
            "Match Number": 562,
            "Damage done": 74.0
        },
        {
            "Match Number": 563,
            "Damage done": 164.0
        },
        {
            "Match Number": 564,
            "Damage done": 90.0
        },
        {
            "Match Number": 565,
            "Damage done": 48.0
        },
        {
            "Match Number": 566,
            "Damage done": 94.0
        },
        {
            "Match Number": 567,
            "Damage done": 54.0
        },
        {
            "Match Number": 568,
            "Damage done": 77.0
        },
        {
            "Match Number": 569,
            "Damage done": 14.0
        },
        {
            "Match Number": 570,
            "Damage done": 101.0
        },
        {
            "Match Number": 571,
            "Damage done": 90.0
        },
        {
            "Match Number": 572,
            "Damage done": 53.0
        },
        {
            "Match Number": 573,
            "Damage done": 48.0
        },
        {
            "Match Number": 574,
            "Damage done": 92.0
        },
        {
            "Match Number": 575,
            "Damage done": 57.0
        },
        {
            "Match Number": 576,
            "Damage done": 135.0
        },
        {
            "Match Number": 577,
            "Damage done": 153.0
        },
        {
            "Match Number": 578,
            "Damage done": 204.0
        },
        {
            "Match Number": 579,
            "Damage done": 57.0
        },
        {
            "Match Number": 580,
            "Damage done": 148.0
        },
        {
            "Match Number": 581,
            "Damage done": 68.0
        },
        {
            "Match Number": 582,
            "Damage done": 93.0
        },
        {
            "Match Number": 583,
            "Damage done": 55.0
        },
        {
            "Match Number": 584,
            "Damage done": 116.0
        },
        {
            "Match Number": 585,
            "Damage done": 131.0
        },
        {
            "Match Number": 586,
            "Damage done": 128.0
        },
        {
            "Match Number": 587,
            "Damage done": 68.0
        },
        {
            "Match Number": 588,
            "Damage done": 0.0
        },
        {
            "Match Number": 589,
            "Damage done": 130.0
        },
        {
            "Match Number": 590,
            "Damage done": 158.0
        },
        {
            "Match Number": 591,
            "Damage done": 48.0
        },
        {
            "Match Number": 592,
            "Damage done": 107.0
        },
        {
            "Match Number": 593,
            "Damage done": 102.0
        },
        {
            "Match Number": 594,
            "Damage done": 112.0
        },
        {
            "Match Number": 595,
            "Damage done": 108.0
        },
        {
            "Match Number": 596,
            "Damage done": 51.0
        },
        {
            "Match Number": 597,
            "Damage done": 104.0
        },
        {
            "Match Number": 598,
            "Damage done": 103.0
        },
        {
            "Match Number": 599,
            "Damage done": 38.0
        },
        {
            "Match Number": 600,
            "Damage done": 0.0
        },
        {
            "Match Number": 601,
            "Damage done": 42.0
        },
        {
            "Match Number": 602,
            "Damage done": 44.0
        },
        {
            "Match Number": 603,
            "Damage done": 147.0
        },
        {
            "Match Number": 604,
            "Damage done": 81.0
        },
        {
            "Match Number": 605,
            "Damage done": 69.0
        },
        {
            "Match Number": 606,
            "Damage done": 219.0
        },
        {
            "Match Number": 607,
            "Damage done": 39.0
        },
        {
            "Match Number": 608,
            "Damage done": 34.0
        },
        {
            "Match Number": 609,
            "Damage done": 133.0
        },
        {
            "Match Number": 610,
            "Damage done": 67.0
        },
        {
            "Match Number": 611,
            "Damage done": 158.0
        },
        {
            "Match Number": 612,
            "Damage done": 78.0
        },
        {
            "Match Number": 613,
            "Damage done": 26.0
        },
        {
            "Match Number": 614,
            "Damage done": 64.0
        },
        {
            "Match Number": 615,
            "Damage done": 0.0
        },
        {
            "Match Number": 616,
            "Damage done": 201.0
        },
        {
            "Match Number": 617,
            "Damage done": 53.0
        },
        {
            "Match Number": 618,
            "Damage done": 87.0
        },
        {
            "Match Number": 619,
            "Damage done": 89.0
        },
        {
            "Match Number": 620,
            "Damage done": 85.0
        },
        {
            "Match Number": 621,
            "Damage done": 90.0
        },
        {
            "Match Number": 622,
            "Damage done": 44.0
        },
        {
            "Match Number": 623,
            "Damage done": 159.0
        },
        {
            "Match Number": 624,
            "Damage done": 110.0
        },
        {
            "Match Number": 625,
            "Damage done": 110.0
        },
        {
            "Match Number": 626,
            "Damage done": 53.0
        },
        {
            "Match Number": 627,
            "Damage done": 36.0
        },
        {
            "Match Number": 628,
            "Damage done": 19.0
        },
        {
            "Match Number": 629,
            "Damage done": 100.0
        },
        {
            "Match Number": 630,
            "Damage done": 162.0
        },
        {
            "Match Number": 631,
            "Damage done": 54.0
        },
        {
            "Match Number": 632,
            "Damage done": 11.0
        },
        {
            "Match Number": 633,
            "Damage done": 52.0
        },
        {
            "Match Number": 634,
            "Damage done": 119.0
        },
        {
            "Match Number": 635,
            "Damage done": 48.0
        },
        {
            "Match Number": 636,
            "Damage done": 14.0
        },
        {
            "Match Number": 637,
            "Damage done": 93.0
        },
        {
            "Match Number": 638,
            "Damage done": 22.0
        },
        {
            "Match Number": 639,
            "Damage done": 90.0
        },
        {
            "Match Number": 640,
            "Damage done": 49.0
        },
        {
            "Match Number": 641,
            "Damage done": 111.0
        },
        {
            "Match Number": 642,
            "Damage done": 125.0
        },
        {
            "Match Number": 643,
            "Damage done": 91.0
        },
        {
            "Match Number": 644,
            "Damage done": 65.0
        },
        {
            "Match Number": 645,
            "Damage done": 50.0
        },
        {
            "Match Number": 646,
            "Damage done": 107.0
        },
        {
            "Match Number": 647,
            "Damage done": 78.0
        },
        {
            "Match Number": 648,
            "Damage done": 1.0
        },
        {
            "Match Number": 649,
            "Damage done": 52.0
        },
        {
            "Match Number": 650,
            "Damage done": 163.0
        },
        {
            "Match Number": 651,
            "Damage done": 116.0
        },
        {
            "Match Number": 652,
            "Damage done": 59.0
        },
        {
            "Match Number": 653,
            "Damage done": 47.0
        },
        {
            "Match Number": 654,
            "Damage done": 53.0
        },
        {
            "Match Number": 655,
            "Damage done": 93.0
        },
        {
            "Match Number": 656,
            "Damage done": 81.0
        },
        {
            "Match Number": 657,
            "Damage done": 87.0
        },
        {
            "Match Number": 658,
            "Damage done": 120.0
        },
        {
            "Match Number": 659,
            "Damage done": 85.0
        },
        {
            "Match Number": 660,
            "Damage done": 119.0
        },
        {
            "Match Number": 661,
            "Damage done": 28.0
        },
        {
            "Match Number": 662,
            "Damage done": 30.0
        },
        {
            "Match Number": 663,
            "Damage done": 146.0
        },
        {
            "Match Number": 664,
            "Damage done": 45.0
        }
    ]
}